畢業專題：Design and Verification of an ECG Analog Front-End and Fixed-Point RTL Filter/ECG_Verilog/RR_detector.v
module RR_detector (
    input wire clk,
    input wire rst_n,
    input wire signed [15:0] data_in,
    output reg peak_flag,
    output reg [31:0] rr_interval,
    output wire [31:0] energy_debug 
);

    parameter THRESHOLD_SQ = 32'd130000000;

    // Refractory Period
    // 500Hz 採樣率 -> 250ms = 125 點
    // 拉長到 250ms 可以有效避開 T 波的誤判
    parameter REFRACTORY_PERIOD = 125; 

    // ============================================================
    
    // 內部變數
    reg [31:0] global_counter;    
    reg [31:0] last_peak_time;
    reg [31:0] refractory_cnt;
    
    // 平方運算 (Squaring) - 讓 R 波更明顯，壓制 T 波與雜訊
    // data_in 是 16-bit, 平方後最大 32-bit (包含符號位其實31-bit)
    wire signed [31:0] data_sq;
    assign data_sq = data_in * data_in;
    
    // 輸出給你看波形用的 (轉成 unsigned 方便觀察)
    assign energy_debug = data_sq;

    always @(posedge clk or negedge rst_n) begin
        if (!rst_n) begin
            global_counter <= 0;
            last_peak_time <= 0;
            rr_interval <= 0;
            peak_flag <= 0;
            refractory_cnt <= 0;
        end 
        else begin
            // 1. 全域時間計數
            global_counter <= global_counter + 1;
            
            // 預設 flag 為 0 (脈衝)
            peak_flag <= 0;

            // 2. 處理不反應期倒數
            if (refractory_cnt > 0) begin
                refractory_cnt <= refractory_cnt - 1;
            end
            
            // 3. 峰值偵測邏輯 (使用平方後的能量 data_sq)
            else if (data_sq > THRESHOLD_SQ && refractory_cnt == 0) begin
                
                // --- 偵測到 R 波 ---
                peak_flag <= 1;
                
                // 計算 RR Interval
                if (last_peak_time != 0) begin
                    rr_interval <= global_counter - last_peak_time;
                end
                
                // 更新時間
                last_peak_time <= global_counter;
                
                // 進入不反應期
                refractory_cnt <= REFRACTORY_PERIOD;
            end
        end
    end

endmodule

畢業專題：Design and Verification of an ECG Analog Front-End and Fixed-Point RTL Filter/ECG_Verilog/fir_filter_bs.v
module FIR_filter_BS (
    input wire clk,
    input wire rst_n,
    input wire data_en,
    input wire signed [15:0] data_in,   // x[n]
    output reg signed [15:0] data_out   // y[n]
);

    reg signed [15:0] h [0:64]; 
    
    initial begin
        // FIR Spec: Fs=500Hz, F_notch=60Hz, Taps=65
        h[0] = -16'd6; 
        h[1] = 16'd2; 
        h[2] = 16'd9; 
        h[3] = 16'd13; 
        h[4] = 16'd10; 
        h[5] = -16'd1; 
        h[6] = -16'd15; 
        h[7] = -16'd24; 
        h[8] = -16'd20; 
        h[9] = -16'd2; 
        h[10] = 16'd24; 
        h[11] = 16'd42; 
        h[12] = 16'd38; 
        h[13] = 16'd10; 
        h[14] = -16'd32; 
        h[15] = -16'd63; 
        h[16] = -16'd62; 
        h[17] = -16'd24; 
        h[18] = 16'd35; 
        h[19] = 16'd82; 
        h[20] = 16'd87; 
        h[21] = 16'd42; 
        h[22] = -16'd32; 
        h[23] = -16'd95; 
        h[24] = -16'd110; 
        h[25] = -16'd63; 
        h[26] = 16'd23; 
        h[27] = 16'd100; 
        h[28] = 16'd125; 
        h[29] = 16'd82; 
        h[30] = -16'd8; 
        h[31] = -16'd95; 
        h[32] = 16'd32623; 
        h[33] = -16'd95; 
        h[34] = -16'd8; 
        h[35] = 16'd82; 
        h[36] = 16'd125; 
        h[37] = 16'd100; 
        h[38] = 16'd23; 
        h[39] = -16'd63; 
        h[40] = -16'd110; 
        h[41] = -16'd95; 
        h[42] = -16'd32; 
        h[43] = 16'd42; 
        h[44] = 16'd87; 
        h[45] = 16'd82; 
        h[46] = 16'd35; 
        h[47] = -16'd24; 
        h[48] = -16'd62; 
        h[49] = -16'd63; 
        h[50] = -16'd32; 
        h[51] = 16'd10; 
        h[52] = 16'd38; 
        h[53] = 16'd42; 
        h[54] = 16'd24; 
        h[55] = -16'd2; 
        h[56] = -16'd20; 
        h[57] = -16'd24; 
        h[58] = -16'd15; 
        h[59] = -16'd1; 
        h[60] = 16'd10; 
        h[61] = 16'd13; 
        h[62] = 16'd9; 
        h[63] = 16'd2; 
        h[64] = -16'd6;  
    end

    reg signed [15:0] x_delay [0:64];
    integer k;

    reg signed [31:0] accumulator; 
    reg signed [31:0] mult_result;
    
    reg signed [31:0] scaled_result;

    always @(posedge clk or negedge rst_n) begin
        if (!rst_n) begin
            data_out <= 0;
            for (k=0; k<65; k=k+1) x_delay[k] <= 0;
        end 
        else if (data_en) begin
            // Shift
            for (k=64; k>0; k=k-1) begin
                x_delay[k] <= x_delay[k-1];
            end
            
            x_delay[0] <= data_in;

            // Convolution
            accumulator = 0; 
            for (k=0; k<65; k=k+1) begin
                mult_result = x_delay[k] * h[k];
                accumulator = accumulator + mult_result;
            end

            scaled_result = accumulator >>> 15;

            if (scaled_result > 32767) begin
                data_out <= 32767;
            end

            else if (scaled_result < -32768) begin
                data_out <= -32768;
            end

            else begin
                data_out <= scaled_result[15:0];
            end
        end
    end
endmodule

畢業專題：Design and Verification of an ECG Analog Front-End and Fixed-Point RTL Filter/ECG_Verilog/fir_filter.v
module FIR_filter (
    input wire clk,
    input wire rst_n,
    input wire data_en,
    input wire signed [15:0] data_in,   // x[n]
    output reg signed [15:0] data_out   // y[n]
);

    reg signed [15:0] h [0:63]; 
    
    initial begin
        // FIR Spec: Fs=500Hz, Fc=40Hz, Taps=64
        h[0] = -16'd3; 
        h[1] = 16'd10; 
        h[2] = 16'd24; 
        h[3] = 16'd36; 
        h[4] = 16'd42; 
        h[5] = 16'd37; 
        h[6] = 16'd16; 
        h[7] = -16'd20; 
        h[8] = -16'd66; 
        h[9] = -16'd111; 
        h[10] = -16'd138; 
        h[11] = -16'd129; 
        h[12] = -16'd73; 
        h[13] = 16'd29; 
        h[14] = 16'd161; 
        h[15] = 16'd289; 
        h[16] = 16'd370; 
        h[17] = 16'd362; 
        h[18] = 16'd239; 
        h[19] = -16'd0; 
        h[20] = -16'd318; 
        h[21] = -16'd644; 
        h[22] = -16'd884; 
        h[23] = -16'd935; 
        h[24] = -16'd715; 
        h[25] = -16'd182; 
        h[26] = 16'd650; 
        h[27] = 16'd1701; 
        h[28] = 16'd2840; 
        h[29] = 16'd3903; 
        h[30] = 16'd4725; 
        h[31] = 16'd5173; 
        h[32] = 16'd5173; 
        h[33] = 16'd4725; 
        h[34] = 16'd3903; 
        h[35] = 16'd2840; 
        h[36] = 16'd1701; 
        h[37] = 16'd650; 
        h[38] = -16'd182; 
        h[39] = -16'd715; 
        h[40] = -16'd935; 
        h[41] = -16'd884; 
        h[42] = -16'd644; 
        h[43] = -16'd318; 
        h[44] = -16'd0; 
        h[45] = 16'd239; 
        h[46] = 16'd362; 
        h[47] = 16'd370; 
        h[48] = 16'd289; 
        h[49] = 16'd161; 
        h[50] = 16'd29; 
        h[51] = -16'd73; 
        h[52] = -16'd129; 
        h[53] = -16'd138; 
        h[54] = -16'd111; 
        h[55] = -16'd66; 
        h[56] = -16'd20; 
        h[57] = 16'd16; 
        h[58] = 16'd37; 
        h[59] = 16'd42; 
        h[60] = 16'd36; 
        h[61] = 16'd24; 
        h[62] = 16'd10; 
        h[63] = -16'd3; 
    end

    reg signed [15:0] x_delay [0:63];
    integer k;

    reg signed [31:0] accumulator; 
    reg signed [31:0] mult_result;
    
    reg signed [31:0] scaled_result;

    always @(posedge clk or negedge rst_n) begin
        if (!rst_n) begin
            data_out <= 0;
            for (k=0; k<64; k=k+1) x_delay[k] <= 0;
        end 
        else if (data_en) begin
            // Shift
            for (k=63; k>0; k=k-1) begin
                x_delay[k] <= x_delay[k-1];
            end
            
            x_delay[0] <= data_in;

            // Convolution
            accumulator = 0; 
            for (k=0; k<64; k=k+1) begin
                mult_result = x_delay[k] * h[k];
                accumulator = accumulator + mult_result;
            end

            scaled_result = accumulator >>> 15;

            if (scaled_result > 32767) begin
                data_out <= 32767;
            end

            else if (scaled_result < -32768) begin
                data_out <= -32768;
            end

            else begin
                data_out <= scaled_result[15:0];
            end
        end
    end
endmodule

畢業專題：Design and Verification of an ECG Analog Front-End and Fixed-Point RTL Filter/ECG_Verilog/fir_filter_hp.v
module FIR_filter_hp (
    input wire clk,
    input wire rst_n,
    input wire data_en,
    input wire signed [15:0] data_in,   // x[n]
    output reg signed [15:0] data_out   // y[n]
);

    reg signed [15:0] h [0:126]; 
    
    initial begin
        // FIR Spec: High Pass, Fs=500Hz, Fc=5Hz, Taps=127
        h[0] = 16'd10; 
        h[1] = 16'd9; 
        h[2] = 16'd9; 
        h[3] = 16'd9; 
        h[4] = 16'd8; 
        h[5] = 16'd8; 
        h[6] = 16'd8; 
        h[7] = 16'd7; 
        h[8] = 16'd7; 
        h[9] = 16'd6; 
        h[10] = 16'd5; 
        h[11] = 16'd4; 
        h[12] = 16'd2; 
        h[13] = 16'd0; 
        h[14] = -16'd3; 
        h[15] = -16'd6; 
        h[16] = -16'd9; 
        h[17] = -16'd13; 
        h[18] = -16'd18; 
        h[19] = -16'd24; 
        h[20] = -16'd30; 
        h[21] = -16'd37; 
        h[22] = -16'd45; 
        h[23] = -16'd54; 
        h[24] = -16'd63; 
        h[25] = -16'd74; 
        h[26] = -16'd85; 
        h[27] = -16'd98; 
        h[28] = -16'd111; 
        h[29] = -16'd125; 
        h[30] = -16'd140; 
        h[31] = -16'd156; 
        h[32] = -16'd173; 
        h[33] = -16'd190; 
        h[34] = -16'd208; 
        h[35] = -16'd227; 
        h[36] = -16'd246; 
        h[37] = -16'd266; 
        h[38] = -16'd287; 
        h[39] = -16'd307; 
        h[40] = -16'd328; 
        h[41] = -16'd349; 
        h[42] = -16'd371; 
        h[43] = -16'd392; 
        h[44] = -16'd413; 
        h[45] = -16'd434; 
        h[46] = -16'd454; 
        h[47] = -16'd474; 
        h[48] = -16'd494; 
        h[49] = -16'd512; 
        h[50] = -16'd530; 
        h[51] = -16'd548; 
        h[52] = -16'd564; 
        h[53] = -16'd579; 
        h[54] = -16'd593; 
        h[55] = -16'd606; 
        h[56] = -16'd617; 
        h[57] = -16'd627; 
        h[58] = -16'd636; 
        h[59] = -16'd643; 
        h[60] = -16'd648; 
        h[61] = -16'd652; 
        h[62] = -16'd655; 
        h[63] = 16'd32122; 
        h[64] = -16'd655; 
        h[65] = -16'd652; 
        h[66] = -16'd648; 
        h[67] = -16'd643; 
        h[68] = -16'd636; 
        h[69] = -16'd627; 
        h[70] = -16'd617; 
        h[71] = -16'd606; 
        h[72] = -16'd593; 
        h[73] = -16'd579; 
        h[74] = -16'd564; 
        h[75] = -16'd548; 
        h[76] = -16'd530; 
        h[77] = -16'd512; 
        h[78] = -16'd494; 
        h[79] = -16'd474; 
        h[80] = -16'd454; 
        h[81] = -16'd434; 
        h[82] = -16'd413; 
        h[83] = -16'd392; 
        h[84] = -16'd371; 
        h[85] = -16'd349; 
        h[86] = -16'd328; 
        h[87] = -16'd307; 
        h[88] = -16'd287; 
        h[89] = -16'd266; 
        h[90] = -16'd246; 
        h[91] = -16'd227; 
        h[92] = -16'd208; 
        h[93] = -16'd190; 
        h[94] = -16'd173; 
        h[95] = -16'd156; 
        h[96] = -16'd140; 
        h[97] = -16'd125; 
        h[98] = -16'd111; 
        h[99] = -16'd98; 
        h[100] = -16'd85; 
        h[101] = -16'd74; 
        h[102] = -16'd63; 
        h[103] = -16'd54; 
        h[104] = -16'd45; 
        h[105] = -16'd37; 
        h[106] = -16'd30; 
        h[107] = -16'd24; 
        h[108] = -16'd18; 
        h[109] = -16'd13; 
        h[110] = -16'd9; 
        h[111] = -16'd6; 
        h[112] = -16'd3; 
        h[113] = 16'd0; 
        h[114] = 16'd2; 
        h[115] = 16'd4; 
        h[116] = 16'd5; 
        h[117] = 16'd6; 
        h[118] = 16'd7; 
        h[119] = 16'd7; 
        h[120] = 16'd8; 
        h[121] = 16'd8; 
        h[122] = 16'd8; 
        h[123] = 16'd9; 
        h[124] = 16'd9; 
        h[125] = 16'd9; 
        h[126] = 16'd10; 
 
    end

    reg signed [15:0] x_delay [0:127];
    integer k;

    reg signed [31:0] accumulator; 
    reg signed [31:0] mult_result;
    
    reg signed [31:0] scaled_result;

    always @(posedge clk or negedge rst_n) begin
        if (!rst_n) begin
            data_out <= 0;
            for (k=0; k<127; k=k+1) x_delay[k] <= 0;
        end 
        else if (data_en) begin
            // Shift
            for (k=126; k>0; k=k-1) begin
                x_delay[k] <= x_delay[k-1];
            end
            
            x_delay[0] <= data_in;

            // Convolution
            accumulator = 0; 
            for (k=0; k<127; k=k+1) begin
                mult_result = x_delay[k] * h[k];
                accumulator = accumulator + mult_result;
            end

            scaled_result = accumulator >>> 15;

            if (scaled_result > 32767) begin
                data_out <= 32767;
            end

            else if (scaled_result < -32768) begin
                data_out <= -32768;
            end

            else begin
                data_out <= scaled_result[15:0];
            end
        end
    end
endmodule

畢業專題：Design and Verification of an ECG Analog Front-End and Fixed-Point RTL Filter/ECG_Verilog/ADC.v
module adc (
    input wire clk,             // Sampling Clock
    input wire rst_n,           // reset_negedge
    input wire data_en,
    output reg [15:0] data_out  // 16-bits output
);

    reg [15:0] memory [0:65535];
    integer idx;

    initial begin
        $readmemh("ecg_input.hex", memory);
        idx = 0;
        data_out = 0;
    end

    always @(posedge clk or negedge rst_n) begin
        if (!rst_n) begin
            idx <= 0;
            data_out <= 0;
        end

        else if (data_en) begin
            data_out <= memory[idx];
            if (idx < 65535) 
                idx <= idx + 1;
            else 
                idx <= 0;
        end
    end
endmodule

畢業專題：Design and Verification of an ECG Analog Front-End and Fixed-Point RTL Filter/ECG_Verilog/tbECG.v
`timescale 1ms/100us

`include "ADC.v"
`include "fir_filter_hp.v"   // HP
`include "fir_filter.v"      // LP
`include "fir_filter_bs.v"   // NOTCH
`include "RR_detector.v"     // RR

module tb_system;
    reg clk;
    reg rst_n;

    wire signed [15:0] raw_data;
    wire signed [15:0] hp_data;
    wire signed [15:0] lp_data;
    wire signed [15:0] final_data;
    
    wire [31:0] energy_waveform;
    wire peak_flag;
    wire [31:0] rr_count;
    real rr_time_ms;

    initial clk = 0;
    always #1 clk = ~clk; 

    adc u_adc (
        .clk(clk),
        .rst_n(rst_n),
        .data_en(1'b1), 
        .data_out(raw_data)
    );
    FIR_filter_hp u_hp (
        .clk(clk),
        .rst_n(rst_n),
        .data_en(1'b1),
        .data_in(raw_data), 
        .data_out(hp_data)
    );
    FIR_filter u_lp (
        .clk(clk),
        .rst_n(rst_n),
        .data_en(1'b1),
        .data_in(hp_data), 
        .data_out(lp_data)
    );
    FIR_filter_BS u_notch (
        .clk(clk),
        .rst_n(rst_n),
        .data_en(1'b1),
        .data_in(lp_data),
        .data_out(final_data)
    );
    RR_detector u_rr (
        .clk(clk),
        .rst_n(rst_n),
        .data_in(final_data),
        .peak_flag(peak_flag),
        .rr_interval(rr_count),
        .energy_debug(energy_waveform)
    );

    always @(rr_count) begin
        rr_time_ms = rr_count * 2.0; 
    end

    initial begin
        $dumpfile("wave_ECG_analysis.vcd");
        $dumpvars(0, tb_system);
        
        $display("開始模擬...");
        
        rst_n = 1;
        #0.1 rst_n = 0; // Reset active
        #5   rst_n = 1; // Reset release
        
        #4100; // 跑 4 秒

        $display("模擬結束");
        $finish;
    end

endmodule

畢業專題：Design and Verification of an ECG Analog Front-End and Fixed-Point RTL Filter/ECG_Verilog/wave_ECG_analysis.vcd
$date
	Sun Sep 27 01:45:06 2026
$end
$version
	Icarus Verilog
$end
$timescale
	100us
$end
$scope module tb_system $end
$var wire 32 ! rr_count [31:0] $end
$var wire 16 " raw_data [15:0] $end
$var wire 1 # peak_flag $end
$var wire 16 $ lp_data [15:0] $end
$var wire 16 % hp_data [15:0] $end
$var wire 16 & final_data [15:0] $end
$var wire 32 ' energy_waveform [31:0] $end
$var reg 1 ( clk $end
$var reg 1 ) rst_n $end
$var real 1 * rr_time_ms $end
$scope module u_adc $end
$var wire 1 ( clk $end
$var wire 1 + data_en $end
$var wire 1 ) rst_n $end
$var reg 16 , data_out [15:0] $end
$var integer 32 - idx [31:0] $end
$upscope $end
$scope module u_hp $end
$var wire 1 ( clk $end
$var wire 1 . data_en $end
$var wire 16 / data_in [15:0] $end
$var wire 1 ) rst_n $end
$var reg 32 0 accumulator [31:0] $end
$var reg 16 1 data_out [15:0] $end
$var reg 32 2 mult_result [31:0] $end
$var reg 32 3 scaled_result [31:0] $end
$var integer 32 4 k [31:0] $end
$upscope $end
$scope module u_lp $end
$var wire 1 ( clk $end
$var wire 1 5 data_en $end
$var wire 16 6 data_in [15:0] $end
$var wire 1 ) rst_n $end
$var reg 32 7 accumulator [31:0] $end
$var reg 16 8 data_out [15:0] $end
$var reg 32 9 mult_result [31:0] $end
$var reg 32 : scaled_result [31:0] $end
$var integer 32 ; k [31:0] $end
$upscope $end
$scope module u_notch $end
$var wire 1 ( clk $end
$var wire 1 < data_en $end
$var wire 16 = data_in [15:0] $end
$var wire 1 ) rst_n $end
$var reg 32 > accumulator [31:0] $end
$var reg 16 ? data_out [15:0] $end
$var reg 32 @ mult_result [31:0] $end
$var reg 32 A scaled_result [31:0] $end
$var integer 32 B k [31:0] $end
$upscope $end
$scope module u_rr $end
$var wire 1 ( clk $end
$var wire 16 C data_in [15:0] $end
$var wire 32 D energy_debug [31:0] $end
$var wire 1 ) rst_n $end
$var wire 32 E data_sq [31:0] $end
$var parameter 32 F REFRACTORY_PERIOD $end
$var parameter 32 G THRESHOLD_SQ $end
$var reg 32 H global_counter [31:0] $end
$var reg 32 I last_peak_time [31:0] $end
$var reg 1 # peak_flag $end
$var reg 32 J refractory_cnt [31:0] $end
$var reg 32 K rr_interval [31:0] $end
$upscope $end
$upscope $end
$enddefinitions $end
$comment Show the parameter values. $end
$dumpall
b111101111111010010010000000 G
b1111101 F
$end
#0
$dumpvars
bx K
bx J
bx I
bx H
bx E
bx D
bx C
bx B
bx A
bx @
bx ?
bx >
bx =
1<
bx ;
bx :
bx 9
bx 8
bx 7
bx 6
15
bx 4
bx 3
bx 2
bx 1
bx 0
b0 /
1.
b0 -
b0 ,
1+
r0 *
1)
0(
bx '
bx &
bx %
bx $
x#
b0 "
bx !
$end
#1
b0 %
b0 1
b0 6
b0 $
b0 8
b0 =
b0 '
b0 D
b0 E
b0 &
b0 ?
b0 C
b0 J
0#
b0 !
b0 K
b0 I
b0 H
b1111111 4
b1000000 ;
b1000001 B
0)
#10
b1000001 B
b1000000 ;
b1111111 4
1(
#20
0(
#30
b1111111 4
b1000000 ;
b1000001 B
1(
#40
0(
#50
b1000001 B
b1000000 ;
b1111111 4
1(
#51
1)
#60
0(
#70
b1 -
b101001011 "
b101001011 ,
b101001011 /
b1 H
b0 3
b0 2
b0 0
b1111111 4
b0 :
b0 9
b0 7
b1000000 ;
b0 A
b0 @
b0 >
b1000001 B
1(
#80
0(
#90
b10 H
b10 -
b10100011010 "
b10100011010 ,
b10100011010 /
b1000001 B
b1000000 ;
b1111111 4
1(
#100
0(
#110
b11 -
b10011000001 "
b10011000001 ,
b10011000001 /
b11 H
b110011101110 0
b0 2
b1111111 4
b1000000 ;
b1000001 B
1(
#120
0(
#130
b100 H
b100 -
b1111111011101101 "
b1111111011101101 ,
b1111111011101101 /
b1000001 B
b1000000 ;
b0 2
b11111010100111 0
b1111111 4
1(
#140
0(
#150
b101 -
b1111111111111000 "
b1111111111111000 ,
b1111111111111000 /
b101 H
b0 2
b110100100010111 0
b1111111 4
b1000000 ;
b1000001 B
1(
#160
0(
#170
b110 H
b110 -
b1110011011 "
b1110011011 ,
b1110011011 /
b1000001 B
b1000000 ;
b0 2
b101100110011000 0
b1111111 4
1(
#180
0(
#190
b111 -
b100110011 "
b100110011 ,
b100110011 /
b111 H
b0 2
b101100100010000 0
b1111111 4
b1000000 ;
b1000001 B
1(
#200
0(
#210
b1000 H
b1000 -
b10101110110 "
b10101110110 ,
b10101110110 /
b1000001 B
b1000000 ;
b0 2
b111100000001100 0
b1111111 4
1(
#220
0(
#230
b1001 -
b1111111000011011 "
b1111111000011011 ,
b1111111000011011 /
b1001 H
b0 2
b111101110101110 0
b1111111 4
b1000000 ;
b1000001 B
1(
#240
0(
#250
b1010 H
b1 %
b1 1
b1 6
b1010 -
b1011110011 "
b1011110011 ,
b1011110011 /
b1000001 B
b1000000 ;
b1 3
b0 2
b1011000011011111 0
b1111111 4
1(
#260
0(
#270
b1011 -
b1001001110 "
b1001001110 ,
b1001001110 /
b1011 H
b0 2
b1001001101100101 0
b1111111 4
b1000000 ;
b1000001 B
1(
#280
0(
#290
b1100 H
b1111111111111111 $
b1111111111111111 8
b1111111111111111 =
b1100 -
b11011101101 "
b11011101101 ,
b11011101101 /
b1000001 B
b11111111111111111111111111111111 :
b11111111111111111111111111111101 7
b0 9
b1000000 ;
b0 2
b1010100100100001 0
b1111111 4
1(
#300
0(
#310
b1101 -
b1111101111010011 "
b1111101111010011 ,
b1111101111010011 /
b0 $
b0 8
b0 =
b1101 H
b0 2
b1011011010110101 0
b1111111 4
b0 :
b0 9
b111 7
b1000000 ;
b1000001 B
1(
#320
0(
#330
b1110 H
b1110 -
b101110001 "
b101110001 ,
b101110001 /
b110 >
b0 @
b1000001 B
b0 9
b11111 7
b1000000 ;
b0 2
b1110100100010101 0
b1111111 4
1(
#340
0(
#350
b1111 -
b111000011 "
b111000011 ,
b111000011 /
b1 '
b1 D
b1 E
b1111111111111111 &
b1111111111111111 ?
b1111111111111111 C
b1111 H
b0 2
b1010101101010010 0
b1111111 4
b0 9
b1000011 7
b1000000 ;
b11111111111111111111111111111111 A
b0 @
b11111111111111111111111111111110 >
b1000001 B
1(
#360
0(
#370
b10000 H
b10000 -
b1111100000001111 "
b1111100000001111 ,
b1111100000001111 /
b0 @
b11111111111111111111111111110111 >
b1000001 B
b0 9
b1101101 7
b1000000 ;
b0 2
b1010100101010011 0
b1111111 4
1(
#380
0(
#390
b10001 -
b11011011100 "
b11011011100 ,
b11011011100 /
b10001 H
b0 2
b1001011110100101 0
b1111111 4
b0 9
b10010010 7
b1000000 ;
b0 @
b11111111111111111111111111110011 >
b1000001 B
1(
#400
0(
#410
b10010 H
b0 %
b0 1
b0 6
b10010 -
b110101011010 "
b110101011010 ,
b110101011010 /
b0 @
b11111111111111111111111111110110 >
b1000001 B
b0 9
b10100010 7
b1000000 ;
b0 3
b0 2
b10001000011111 0
b1111111 4
1(
#420
0(
#430
b10011 -
b100000010 "
b100000010 ,
b100000010 /
b0 '
b0 D
b0 E
b0 &
b0 ?
b0 C
b10011 H
b0 2
b100011001100010 0
b1111111 4
b0 9
b10001110 7
b1000000 ;
b0 A
b0 @
b1 >
b1000001 B
1(
#440
0(
#450
b10100 H
b1 %
b1 1
b1 6
b10100 -
b1100111101 "
b1100111101 ,
b1100111101 /
b0 @
b1111 >
b1000001 B
b0 9
b1001111 7
b1000000 ;
b1 3
b0 2
b1001010111011101 0
b1111111 4
1(
#460
0(
#470
b10101 -
b1000100 "
b1000100 ,
b1000100 /
b0 %
b0 1
b0 6
b1111111111111111 $
b1111111111111111 8
b1111111111111111 =
b10101 H
b0 3
b0 2
b101001111110110 0
b1111111 4
b11111111111111111111111111111111 :
b0 9
b11111111111111111111111111010110 7
b1000000 ;
b0 @
b11000 >
b1000001 B
1(
#480
0(
#490
b10110 H
b10110 -
b1111011000 "
b1111011000 ,
b1111011000 /
b0 @
b10100 >
b1000001 B
b0 9
b11111111111111111111111100110001 7
b1000000 ;
b0 2
b11001011111110 0
b1111111 4
1(
#500
0(
#510
b10111 -
b11010010 "
b11010010 ,
b11010010 /
b1111111111111111 %
b1111111111111111 1
b1111111111111111 6
b10111 H
b11111111111111111111111111111111 3
b0 2
b11111111111111111100111010100011 0
b1111111 4
b0 9
b11111111111111111111111010011001 7
b1000000 ;
b0 @
b1000 >
b1000001 B
1(
#520
0(
#530
b11000 H
b1 '
b1 D
b1 E
b1111111111111111 &
b1111111111111111 ?
b1111111111111111 C
b11000 -
b1000010000 "
b1000010000 ,
b1000010000 /
b11111111111111111111111111111111 A
b0 @
b11111111111111111111111111101100 >
b1000001 B
b0 9
b11111111111111111111111000110100 7
b1000000 ;
b0 2
b11111111111111111000000100001100 0
b1111111 4
1(
#540
0(
#550
b11001 -
b100100110101 "
b100100110101 ,
b100100110101 /
b1111111111111110 %
b1111111111111110 1
b1111111111111110 6
b11001 H
b11111111111111111111111111111110 3
b0 2
b11111111111111110001110011110010 0
b1111111 4
b0 9
b11111111111111111111111000111011 7
b1000000 ;
b0 @
b11111111111111111111111111010001 >
b1000001 B
1(
#560
0(
#570
b11010 H
b1111111111111101 %
b1111111111111101 1
b1111111111111101 6
b11010 -
b1111111100111000 "
b1111111100111000 ,
b1111111100111000 /
b0 @
b11111111111111111111111111001000 >
b1000001 B
b0 9
b11111111111111111111111011001000 7
b1000000 ;
b11111111111111111111111111111101 3
b0 2
b11111111111111101001101110110011 0
b1111111 4
1(
#580
0(
#590
b11011 -
b1101111 "
b1101111 ,
b1101111 /
b1111111111111100 %
b1111111111111100 1
b1111111111111100 6
b11011 H
b11111111111111111111111111111100 3
b0 2
b11111111111111100101001111100111 0
b1111111 4
b0 9
b11111111111111111111111111100011 7
b1000000 ;
b0 @
b11111111111111111111111111011010 >
b1000001 B
1(
#600
0(
#610
b11100 H
b0 '
b0 D
b0 E
b0 &
b0 ?
b0 C
b0 $
b0 8
b0 =
b1111111111111011 %
b1111111111111011 1
b1111111111111011 6
b11100 -
b1010010110 "
b1010010110 ,
b1010010110 /
b0 A
b0 @
b101 >
b1000001 B
b0 :
b0 9
b101010111 7
b1000000 ;
b11111111111111111111111111111011 3
b0 2
b11111111111111011000111110011110 0
b1111111 4
1(
#620
0(
#630
b11101 -
b1001110101 "
b1001110101 ,
b1001110101 /
b1111111111111001 %
b1111111111111001 1
b1111111111111001 6
b11101 H
b11111111111111111111111111111001 3
b0 2
b11111111111111001100010000011011 0
b1111111 4
b0 9
b1011000011 7
b1000000 ;
b0 @
b110011 >
b1000001 B
1(
#640
0(
#650
b11110 H
b1111111111110111 %
b1111111111110111 1
b1111111111110111 6
b11110 -
b100011111111 "
b100011111111 ,
b100011111111 /
b0 @
b1000100 >
b1000001 B
b0 9
b1110100110 7
b1000000 ;
b11111111111111111111111111110111 3
b0 2
b11111111111110111111111111100110 0
b1111111 4
1(
#660
0(
#670
b11111 -
b101110000110 "
b101110000110 ,
b101110000110 /
b1111111111110110 %
b1111111111110110 1
b1111111111110110 6
b11111 H
b11111111111111111111111111110110 3
b0 2
b11111111111110110000001100101011 0
b1111111 4
b0 9
b1110000000 7
b1000000 ;
b0 @
b110100 >
b1000001 B
1(
#680
0(
#690
b100000 H
b1111111111110100 %
b1111111111110100 1
b1111111111110100 6
b100000 -
b1111111101001111 "
b1111111101001111 ,
b1111111101001111 /
b0 @
b100 >
b1000001 B
b0 9
b111101011 7
b1000000 ;
b11111111111111111111111111110100 3
b0 2
b11111111111110100011101010111100 0
b1111111 4
1(
#700
0(
#710
b100001 -
b110000110 "
b110000110 ,
b110000110 /
b1111111111110010 %
b1111111111110010 1
b1111111111110010 6
b1111111111111111 $
b1111111111111111 8
b1111111111111111 =
b1 '
b1 D
b1 E
b1111111111111111 &
b1111111111111111 ?
b1111111111111111 C
b100001 H
b11111111111111111111111111110010 3
b0 2
b11111111111110010110000010110100 0
b1111111 4
b11111111111111111111111111111111 :
b0 9
b11111111111111111111111011010001 7
b1000000 ;
b11111111111111111111111111111111 A
b0 @
b11111111111111111111111111001010 >
b1000001 B
1(
#720
0(
#730
b100010 H
b1111111111101111 %
b1111111111101111 1
b1111111111101111 6
b100010 -
b11100011100 "
b11100011100 ,
b11100011100 /
b0 @
b11111111111111111111111110100101 >
b1000001 B
b0 9
b11111111111111111111101010011100 7
b1000000 ;
b11111111111111111111111111101111 3
b0 2
b11111111111101111101111101101011 0
b1111111 4
1(
#740
0(
#750
b100011 -
b10001000001 "
b10001000001 ,
b10001000001 /
b1111111111101100 %
b1111111111101100 1
b1111111111101100 6
b100011 H
b11111111111111111111111111101100 3
b0 2
b11111111111101100110001110100001 0
b1111111 4
b0 9
b11111111111111111111011000100011 7
b1000000 ;
b0 @
b11111111111111111111111110110001 >
b1000001 B
1(
#760
0(
#770
b100100 H
b1111111111101001 %
b1111111111101001 1
b1111111111101001 6
b100100 -
b111011001110 "
b111011001110 ,
b111011001110 /
b0 @
b11111111111111111111111111100000 >
b1000001 B
b0 9
b11111111111111111111001010100011 7
b1000000 ;
b11111111111111111111111111101001 3
b0 2
b11111111111101001111100001011001 0
b1111111 4
1(
#780
0(
#790
b100101 -
b111000101101 "
b111000101101 ,
b111000101101 /
b1111111111100110 %
b1111111111100110 1
b1111111111100110 6
b0 '
b0 D
b0 E
b0 &
b0 ?
b0 C
b100101 H
b11111111111111111111111111100110 3
b0 2
b11111111111100110011110000011101 0
b1111111 4
b0 9
b11111111111111111111000101111010 7
b1000000 ;
b0 A
b0 @
b11110 >
b1000001 B
1(
#800
0(
#810
b100110 H
b1111111111100011 %
b1111111111100011 1
b1111111111100011 6
b100110 -
b101010011010 "
b101010011010 ,
b101010011010 /
b0 @
b1001011 >
b1000001 B
b0 9
b11111111111111111111001111101111 7
b1000000 ;
b11111111111111111111111111100011 3
b0 2
b11111111111100011101001100010110 0
b1111111 4
1(
#820
0(
#830
b100111 -
b101101110100 "
b101101110100 ,
b101101110100 /
b1111111111100000 %
b1111111111100000 1
b1111111111100000 6
b100111 H
b11111111111111111111111111100000 3
b0 2
b11111111111100000000111100100111 0
b1111111 4
b0 9
b11111111111111111111101011100011 7
b1000000 ;
b0 @
b1001110 >
b1000001 B
1(
#840
0(
