課程專題(2)： FPGA Lab/FPGA系統設計實務/CO_ALU(虛擬機執行檔)/ALU.v
// =================================================================
// Homework 3 ： 8-Bit ALU ( Behavioral Model )
// =================================================================

module ALU8bit( Opcode, Operand1, Operand2, Cin, Result, flagC, flagZ);
    // -------------------------------------------------------------
    // Ports Declaration
    // -------------------------------------------------------------
    input [3:0] Opcode;                     // 4-bit Opcode (13種功能需用4bits)
    input [7:0] Operand1, Operand2;         // 8-bit Operand
    input Cin;                              // 1-bit 進位/借位輸入 (用於加法與減法)
    
    output reg [15:0] Result = 16'h0000;    // 16-bit 結果輸出
    output reg flagC = 1'b0,                // Carry flag，預設 0
               flagZ = 1'b0;                // Zero flag)，預設 0

    // -------------------------------------------------------------
    // Parameters for Opcodes
    // -------------------------------------------------------------
    // 運算功能
    parameter [3:0] ADD  = 4'b0000, // 1. Addition 
                    ADDC = 4'b0001, // 2. Addition with carry
                    SUB  = 4'b0010, // 3. Subtraction
                    SUBB = 4'b0011, // 4. Subtraction with borrow
                    DEC  = 4'b0100, // 5. Decrement (遞減)
                    INC  = 4'b0101, // 6. Increment (遞增)
                    TRA  = 4'b0110, // 7. Transfer function (輸出等於輸入，傳遞)
                    AND  = 4'b0111, // 8. Logical AND 
                    OR   = 4'b1000, // 9. Logical OR 
                    XOR  = 4'b1001, // 10. Logical XOR 
                    NOT  = 4'b1010, // 11. Logical NOT
                    SHL  = 4'b1011, // 12. Left shift  (左移 1 位)
                    SHR  = 4'b1100; // 13. Right shift (右移 1 位)

    // -------------------------------------------------------------
    // Combinational Logic
    // -------------------------------------------------------------
    always @ (Opcode or Operand1 or Operand2 or Cin)
    begin
        // ================= 【Arithmetic Unit】 =================
        
        // 1. Addition
        if (Opcode == ADD) begin
            Result = Operand1 + Operand2;
            flagC = Result[8];               // 以結果的第 8 位元(Bit 8)作為進位溢位判定
            flagZ = (Result == 16'h0000);    // 零旗標：當 16-bit 結果全為 0 時拉高
        end
        // 2. Addition with carry
        else if (Opcode == ADDC) begin
            Result = Operand1 + Operand2 + Cin;
            flagC = Result[8];
            flagZ = (Result == 16'h0000);
        end
        // 3. Subtraction
        else if (Opcode == SUB) begin
            Result = Operand1 - Operand2;
            flagC = Result[8];               // 減法借位旗標
            flagZ = (Result == 16'h0000);
        end
        // 4. Subtraction with borrow
        else if (Opcode == SUBB) begin
            Result = Operand1 - Operand2 - Cin;
            flagC = Result[8];
            flagZ = (Result == 16'h0000);
        end
        // 5. Decrement
        else if (Opcode == DEC) begin
            Result = Operand1 - 1'b1;
            flagC = Result[8];
            flagZ = (Result == 16'h0000);
        end
        // 6. Increment
        else if (Opcode == INC) begin
            Result = Operand1 + 1'b1;
            flagC = Result[8];
            flagZ = (Result == 16'h0000);
        end
        // 7. Transfer A
        else if (Opcode == TRA) begin
            Result = Operand1;               // 直接將運算元 1 傳送到輸出
            flagC = 1'b0;                    // 轉移無進位，清除 flagC
            flagZ = (Result == 16'h0000);
        end
        
        // ================= 【Logic Unit】 =================
        // 純邏輯運算不影響/不變更 flagC 的數值
        
        // 8. 邏輯 AND
        else if (Opcode == AND) begin
            Result = Operand1 & Operand2;
            flagZ = (Result == 16'h0000);
        end
        // 9. 邏輯 OR
        else if (Opcode == OR) begin
            Result = Operand1 | Operand2;
            flagZ = (Result == 16'h0000);
        end
        // 10. 邏輯 XOR
        else if (Opcode == XOR) begin
            Result = Operand1 ^ Operand2;
            flagZ = (Result == 16'h0000);
        end
        // 11. 邏輯 NOT
        else if (Opcode == NOT) begin
            Result = ~Operand1;
            flagZ = (Result == 16'h0000);
        end
        
        // ================= 【Shift Unit】 =================
        
        // 12. Left Shift
        else if (Opcode == SHL) begin
            Result = Operand1 << 1;
            flagC = Operand1[7];             // 左移時，原本的最高位元(Bit 7)會被擠出去，移入進位旗標
            flagZ = (Result == 16'h0000);
        end
        // 13. Right Shift
        else if (Opcode == SHR) begin
            Result = Operand1 >> 1;
            flagC = Operand1[0];             // 右移時，原本的最低位元(Bit 0)會被擠出去，移入進位旗標
            flagZ = (Result == 16'h0000);
        end
        
        // ================= 【Default Case】 =================
        else begin
            Result = 16'h0000;
            flagC = 1'b0;
            flagZ = 1'b0;
        end
    end
endmodule

課程專題(2)： FPGA Lab/FPGA系統設計實務/CO_ALU(虛擬機執行檔)/ALU_tb.v
`timescale 1ns/100ps    // 設定時間單位為 1ns，時間精度為 100ps
`include "ALU.v"        // 導入 ALU 模組檔名

module ALU8bit_tb;

    // Inputs
    reg [3:0] Opcode;
    reg [7:0] Operand1;
    reg [7:0] Operand2;
    reg Cin;

    // Outputs
    wire [15:0] Result;
    wire flagC;
    wire flagZ;

    // Temporary variable (內部計數)
    reg [3:0] count = 4'b0000;

    // Instantiate the Unit Under Test (UUT)
    ALU8bit uut (
        .Opcode(Opcode), 
        .Operand1(Operand1), 
        .Operand2(Operand2), 
        .Cin(Cin),
        .Result(Result), 
        .flagC(flagC), 
        .flagZ(flagZ)
    ); 

    initial begin
        // Initialize Inputs (初始化)
        Opcode = 4'b0000;
        Operand1 = 8'h00;
        Operand2 = 8'h00;
        Cin = 1'b0;

        // 等待 100 ns 讓全域重置完成
        #100; 
        
        // Stimulus
        Operand1 = 8'hAA;   // 二進位: 10101010
        Operand2 = 8'h55;   // 二進位: 01010101
        Cin = 1'b1;         // 測試帶進位加減法時使用
        
        // 利用 for 迴圈自動掃描 13 種 Opcode 運算結果
        for (count = 0; count < 13; count = count + 1'b1) begin
            Opcode = count;
            #20;            // 每隔 20ns 變換一次運算功能
        end
        
        $finish;            // 結束模擬
    end

    // =================================================================
    // Terminal Monitor
    // =================================================================
    initial begin
        $display("-------------------------------------------------------------------------------------------------------");
        $display(" 時間(Time) | Opcode | Operand1 (十六/十進位) | Operand2 (十六/十進位) | Cin =>  Result (十六進位) |  C  |  Z ");
        $display("-------------------------------------------------------------------------------------------------------");
        
        $monitor("%8t ns |  %b  |    %h    (%3d)     |    %h    (%3d)     |  %b  =>      %h        |  %b  |  %b ", 
                 $time,     Opcode,  Operand1, Operand1,  Operand2, Operand2,  Cin,    Result,            flagC, flagZ);
    end

    initial begin
        $dumpfile("ALU_wave.vcd");
        $dumpvars(0, ALU8bit_tb);
    end
    
endmodule

課程專題(2)： FPGA Lab/FPGA系統設計實務/CO_ALU(虛擬機執行檔)/ALU_wave.vcd
$date
   Tue Sep 22 14:13:02 2026
$end
$version
  P.20131013
$end
$timescale
  1ps
$end
$scope module ALU8bit_tb $end
$var wire 1 ! Result [15] $end
$var wire 1 " Result [14] $end
$var wire 1 # Result [13] $end
$var wire 1 $ Result [12] $end
$var wire 1 % Result [11] $end
$var wire 1 & Result [10] $end
$var wire 1 ' Result [9] $end
$var wire 1 ( Result [8] $end
$var wire 1 ) Result [7] $end
$var wire 1 * Result [6] $end
$var wire 1 + Result [5] $end
$var wire 1 , Result [4] $end
$var wire 1 - Result [3] $end
$var wire 1 . Result [2] $end
$var wire 1 / Result [1] $end
$var wire 1 0 Result [0] $end
$var wire 1 1 flagC $end
$var wire 1 2 flagZ $end
$var reg 4 3 Opcode [3:0] $end
$var reg 8 4 Operand1 [7:0] $end
$var reg 8 5 Operand2 [7:0] $end
$var reg 1 6 Cin $end
$var reg 4 7 count [3:0] $end
$scope module uut $end
$var wire 1 8 Opcode [3] $end
$var wire 1 9 Opcode [2] $end
$var wire 1 : Opcode [1] $end
$var wire 1 ; Opcode [0] $end
$var wire 1 < Operand1 [7] $end
$var wire 1 = Operand1 [6] $end
$var wire 1 > Operand1 [5] $end
$var wire 1 ? Operand1 [4] $end
$var wire 1 @ Operand1 [3] $end
$var wire 1 A Operand1 [2] $end
$var wire 1 B Operand1 [1] $end
$var wire 1 C Operand1 [0] $end
$var wire 1 D Operand2 [7] $end
$var wire 1 E Operand2 [6] $end
$var wire 1 F Operand2 [5] $end
$var wire 1 G Operand2 [4] $end
$var wire 1 H Operand2 [3] $end
$var wire 1 I Operand2 [2] $end
$var wire 1 J Operand2 [1] $end
$var wire 1 K Operand2 [0] $end
$var wire 1 L Cin $end
$var reg 16 M Result [15:0] $end
$var reg 1 N flagC $end
$var reg 1 O flagZ $end
$upscope $end
$upscope $end
$enddefinitions $end
#0
$dumpvars
b0 3
b0 4
b0 5
06
b0 7
0$
0#
0"
0!
01
12
b0 M
0N
1O
0.
0-
0,
0+
0*
0)
0(
0'
0&
0%
0=
0<
0K
0J
0I
0H
0G
0F
0E
0D
09
08
0C
0B
0A
0@
0?
0>
0L
00
0/
0;
0:
$end
#100000
b10101010 4
b1010101 5
16
02
b11111111 M
0O
1.
1-
1,
1+
1*
1)
1<
1K
1I
1G
1E
1B
1@
1>
1L
10
1/
#120000
b1 3
b1 7
11
b100000000 M
1N
0.
0-
0,
0+
0*
0)
1(
00
0/
1;
#140000
b10 3
b10 7
01
b1010101 M
0N
1.
1,
1*
0(
10
0;
1:
#160000
b11 3
b11 7
b1010100 M
00
1;
#180000
b100 3
b100 7
b10101001 M
0.
1-
0,
1+
0*
1)
19
10
0;
0:
#200000
b101 3
b101 7
b10101011 M
1/
1;
#220000
b110 3
b110 7
b10101010 M
00
0;
1:
#240000
b111 3
b111 7
12
b0 M
1O
0-
0+
0)
0/
1;
#260000
b1000 3
b1000 7
02
b11111111 M
0O
1.
1-
1,
1+
1*
1)
09
18
10
1/
0;
0:
#280000
b1001 3
b1001 7
1;
#300000
b1010 3
b1010 7
1$
1#
1"
1!
b1111111101010101 M
0-
0+
0)
1(
1'
1&
1%
0/
0;
1:
#320000
b1011 3
b1011 7
0$
0#
0"
0!
11
b101010100 M
1N
0'
0&
0%
00
1;
#340000
b1100 3
b1100 7
01
b1010101 M
0N
0(
19
10
0;
0:
#360000
b1101 7
